[{"id":"延庆县","amount":{"341":{"x":115.7437,"y":40.4995,"region":"延庆县","Distribution":"39370"} ,"342":{"x":115.7437,"y":40.5195,"region":"延庆县","Distribution":"15540"} ,"376":{"x":115.7637,"y":40.4995,"region":"延庆县","Distribution":"22641"} ,"377":{"x":115.7637,"y":40.5195,"region":"延庆县","Distribution":"10177"} ,"378":{"x":115.7637,"y":40.5395,"region":"延庆县","Distribution":"1225"} ,"412":{"x":115.7837,"y":40.4395,"region":"延庆县","Distribution":"9747"} ,"413":{"x":115.7837,"y":40.4595,"region":"延庆县","Distribution":"37984"} ,"414":{"x":115.7837,"y":40.4795,"region":"延庆县","Distribution":"57194"} ,"415":{"x":115.7837,"y":40.4995,"region":"延庆县","Distribution":"1080"} ,"416":{"x":115.7837,"y":40.5195,"region":"延庆县","Distribution":"17703"} ,"417":{"x":115.7837,"y":40.5395,"region":"延庆县","Distribution":"67386"} ,"450":{"x":115.8037,"y":40.4395,"region":"延庆县","Distribution":"33069"} ,"451":{"x":115.8037,"y":40.4595,"region":"延庆县","Distribution":"8144"} ,"452":{"x":115.8037,"y":40.4795,"region":"延庆县","Distribution":"10129"} ,"453":{"x":115.8037,"y":40.4995,"region":"延庆县","Distribution":"33567"} ,"454":{"x":115.8037,"y":40.5195,"region":"延庆县","Distribution":"7943"} ,"455":{"x":115.8037,"y":40.5395,"region":"延庆县","Distribution":"44993"} ,"488":{"x":115.8237,"y":40.3995,"region":"延庆县","Distribution":"29414"} ,"489":{"x":115.8237,"y":40.4195,"region":"延庆县","Distribution":"10359"} ,"490":{"x":115.8237,"y":40.4395,"region":"延庆县","Distribution":"2501"} ,"491":{"x":115.8237,"y":40.4595,"region":"延庆县","Distribution":"9650"} ,"492":{"x":115.8237,"y":40.4795,"region":"延庆县","Distribution":"5275"} ,"493":{"x":115.8237,"y":40.4995,"region":"延庆县","Distribution":"18423"} ,"494":{"x":115.8237,"y":40.5195,"region":"延庆县","Distribution":"21103"} ,"495":{"x":115.8237,"y":40.5395,"region":"延庆县","Distribution":"1174"} ,"496":{"x":115.8237,"y":40.5595,"region":"延庆县","Distribution":"62078"} ,"527":{"x":115.8437,"y":40.3795,"region":"延庆县","Distribution":"57244"} ,"528":{"x":115.8437,"y":40.3995,"region":"延庆县","Distribution":"50154"} ,"529":{"x":115.8437,"y":40.4195,"region":"延庆县","Distribution":"2426"} ,"530":{"x":115.8437,"y":40.4395,"region":"延庆县","Distribution":"1673"} ,"531":{"x":115.8437,"y":40.4595,"region":"延庆县","Distribution":"1554"} ,"532":{"x":115.8437,"y":40.4795,"region":"延庆县","Distribution":"12653"} ,"533":{"x":115.8437,"y":40.4995,"region":"延庆县","Distribution":"7053"} ,"534":{"x":115.8437,"y":40.5195,"region":"延庆县","Distribution":"14910"} ,"535":{"x":115.8437,"y":40.5395,"region":"延庆县","Distribution":"13646"} ,"536":{"x":115.8437,"y":40.5595,"region":"延庆县","Distribution":"2001"} ,"537":{"x":115.8437,"y":40.5795,"region":"延庆县","Distribution":"2989"} ,"570":{"x":115.8637,"y":40.3795,"region":"延庆县","Distribution":"25949"} ,"571":{"x":115.8637,"y":40.3995,"region":"延庆县","Distribution":"19195"} ,"572":{"x":115.8637,"y":40.4195,"region":"延庆县","Distribution":"66842"} ,"573":{"x":115.8637,"y":40.4395,"region":"延庆县","Distribution":"17002"} ,"574":{"x":115.8637,"y":40.4595,"region":"延庆县","Distribution":"12761"} ,"575":{"x":115.8637,"y":40.4795,"region":"延庆县","Distribution":"4799"} ,"576":{"x":115.8637,"y":40.4995,"region":"延庆县","Distribution":"13815"} ,"577":{"x":115.8637,"y":40.5195,"region":"延庆县","Distribution":"87052"} ,"578":{"x":115.8637,"y":40.5395,"region":"延庆县","Distribution":"57769"} ,"579":{"x":115.8637,"y":40.5595,"region":"延庆县","Distribution":"20304"} ,"580":{"x":115.8637,"y":40.5795,"region":"延庆县","Distribution":"24548"} ,"614":{"x":115.8837,"y":40.3795,"region":"延庆县","Distribution":"12235"} ,"615":{"x":115.8837,"y":40.3995,"region":"延庆县","Distribution":"8023"} ,"616":{"x":115.8837,"y":40.4195,"region":"延庆县","Distribution":"30205"} ,"617":{"x":115.8837,"y":40.4395,"region":"延庆县","Distribution":"20983"} ,"618":{"x":115.8837,"y":40.4595,"region":"延庆县","Distribution":"21183"} ,"619":{"x":115.8837,"y":40.4795,"region":"延庆县","Distribution":"39789"} ,"620":{"x":115.8837,"y":40.4995,"region":"延庆县","Distribution":"2839"} ,"621":{"x":115.8837,"y":40.5195,"region":"延庆县","Distribution":"1618"} ,"622":{"x":115.8837,"y":40.5395,"region":"延庆县","Distribution":"27371"} ,"623":{"x":115.8837,"y":40.5595,"region":"延庆县","Distribution":"7522"} ,"624":{"x":115.8837,"y":40.5795,"region":"延庆县","Distribution":"63451"} ,"658":{"x":115.9037,"y":40.3795,"region":"延庆县","Distribution":"75805"} ,"659":{"x":115.9037,"y":40.3995,"region":"延庆县","Distribution":"83939"} ,"660":{"x":115.9037,"y":40.4195,"region":"延庆县","Distribution":"25647"} ,"661":{"x":115.9037,"y":40.4395,"region":"延庆县","Distribution":"38760"} ,"662":{"x":115.9037,"y":40.4595,"region":"延庆县","Distribution":"28419"} ,"663":{"x":115.9037,"y":40.4795,"region":"延庆县","Distribution":"41918"} ,"664":{"x":115.9037,"y":40.4995,"region":"延庆县","Distribution":"48653"} ,"665":{"x":115.9037,"y":40.5195,"region":"延庆县","Distribution":"3947"} ,"666":{"x":115.9037,"y":40.5395,"region":"延庆县","Distribution":"55871"} ,"667":{"x":115.9037,"y":40.5595,"region":"延庆县","Distribution":"29900"} ,"668":{"x":115.9037,"y":40.5795,"region":"延庆县","Distribution":"39447"} ,"669":{"x":115.9037,"y":40.5995,"region":"延庆县","Distribution":"18455"} ,"703":{"x":115.9237,"y":40.3395,"region":"延庆县","Distribution":"13235"} ,"704":{"x":115.9237,"y":40.3595,"region":"延庆县","Distribution":"2323"} ,"705":{"x":115.9237,"y":40.3795,"region":"延庆县","Distribution":"83832"} ,"706":{"x":115.9237,"y":40.3995,"region":"延庆县","Distribution":"418"} ,"707":{"x":115.9237,"y":40.4195,"region":"延庆县","Distribution":"76768"} ,"708":{"x":115.9237,"y":40.4395,"region":"延庆县","Distribution":"11623"} ,"709":{"x":115.9237,"y":40.4595,"region":"延庆县","Distribution":"2049"} ,"710":{"x":115.9237,"y":40.4795,"region":"延庆县","Distribution":"989"} ,"711":{"x":115.9237,"y":40.4995,"region":"延庆县","Distribution":"62567"} ,"712":{"x":115.9237,"y":40.5195,"region":"延庆县","Distribution":"24453"} ,"713":{"x":115.9237,"y":40.5395,"region":"延庆县","Distribution":"31"} ,"714":{"x":115.9237,"y":40.5595,"region":"延庆县","Distribution":"29080"} ,"715":{"x":115.9237,"y":40.5795,"region":"延庆县","Distribution":"52224"} ,"716":{"x":115.9237,"y":40.5995,"region":"延庆县","Distribution":"23261"} ,"751":{"x":115.9437,"y":40.2995,"region":"延庆县","Distribution":"5172"} ,"752":{"x":115.9437,"y":40.3195,"region":"延庆县","Distribution":"43918"} ,"753":{"x":115.9437,"y":40.3395,"region":"延庆县","Distribution":"18696"} ,"754":{"x":115.9437,"y":40.3595,"region":"延庆县","Distribution":"22326"} ,"755":{"x":115.9437,"y":40.3795,"region":"延庆县","Distribution":"11634"} ,"756":{"x":115.9437,"y":40.3995,"region":"延庆县","Distribution":"24722"} ,"757":{"x":115.9437,"y":40.4195,"region":"延庆县","Distribution":"11047"} ,"758":{"x":115.9437,"y":40.4395,"region":"延庆县","Distribution":"1964"} ,"759":{"x":115.9437,"y":40.4595,"region":"延庆县","Distribution":"2186"} ,"760":{"x":115.9437,"y":40.4795,"region":"延庆县","Distribution":"3823"} ,"761":{"x":115.9437,"y":40.4995,"region":"延庆县","Distribution":"8889"} ,"762":{"x":115.9437,"y":40.5195,"region":"延庆县","Distribution":"67"} ,"763":{"x":115.9437,"y":40.5395,"region":"延庆县","Distribution":"53392"} ,"764":{"x":115.9437,"y":40.5595,"region":"延庆县","Distribution":"17091"} ,"765":{"x":115.9437,"y":40.5795,"region":"延庆县","Distribution":"20625"} ,"766":{"x":115.9437,"y":40.5995,"region":"延庆县","Distribution":"438"} ,"801":{"x":115.9637,"y":40.2795,"region":"延庆县","Distribution":"5323"} ,"802":{"x":115.9637,"y":40.2995,"region":"延庆县","Distribution":"3871"} ,"803":{"x":115.9637,"y":40.3195,"region":"延庆县","Distribution":"22491"} ,"804":{"x":115.9637,"y":40.3395,"region":"延庆县","Distribution":"29269"} ,"805":{"x":115.9637,"y":40.3595,"region":"延庆县","Distribution":"23368"} ,"806":{"x":115.9637,"y":40.3795,"region":"延庆县","Distribution":"37532"} ,"807":{"x":115.9637,"y":40.3995,"region":"延庆县","Distribution":"5857"} ,"808":{"x":115.9637,"y":40.4195,"region":"延庆县","Distribution":"47781"} ,"809":{"x":115.9637,"y":40.4395,"region":"延庆县","Distribution":"24444"} ,"810":{"x":115.9637,"y":40.4595,"region":"延庆县","Distribution":"270"} ,"811":{"x":115.9637,"y":40.4795,"region":"延庆县","Distribution":"47483"} ,"812":{"x":115.9637,"y":40.4995,"region":"延庆县","Distribution":"43719"} ,"813":{"x":115.9637,"y":40.5195,"region":"延庆县","Distribution":"2926"} ,"814":{"x":115.9637,"y":40.5395,"region":"延庆县","Distribution":"12323"} ,"815":{"x":115.9637,"y":40.5595,"region":"延庆县","Distribution":"24450"} ,"816":{"x":115.9637,"y":40.5795,"region":"延庆县","Distribution":"16690"} ,"817":{"x":115.9637,"y":40.5995,"region":"延庆县","Distribution":"13076"} ,"853":{"x":115.9837,"y":40.2995,"region":"延庆县","Distribution":"9465"} ,"855":{"x":115.9837,"y":40.3395,"region":"延庆县","Distribution":"17190"} ,"856":{"x":115.9837,"y":40.3595,"region":"延庆县","Distribution":"11327"} ,"857":{"x":115.9837,"y":40.3795,"region":"延庆县","Distribution":"2559"} ,"858":{"x":115.9837,"y":40.3995,"region":"延庆县","Distribution":"10477"} ,"859":{"x":115.9837,"y":40.4195,"region":"延庆县","Distribution":"52245"} ,"860":{"x":115.9837,"y":40.4395,"region":"延庆县","Distribution":"1083"} ,"861":{"x":115.9837,"y":40.4595,"region":"延庆县","Distribution":"13061"} ,"862":{"x":115.9837,"y":40.4795,"region":"延庆县","Distribution":"59592"} ,"863":{"x":115.9837,"y":40.4995,"region":"延庆县","Distribution":"59371"} ,"864":{"x":115.9837,"y":40.5195,"region":"延庆县","Distribution":"11591"} ,"865":{"x":115.9837,"y":40.5395,"region":"延庆县","Distribution":"13784"} ,"866":{"x":115.9837,"y":40.5595,"region":"延庆县","Distribution":"6970"} ,"905":{"x":116.0037,"y":40.3395,"region":"延庆县","Distribution":"2645"} ,"906":{"x":116.0037,"y":40.3595,"region":"延庆县","Distribution":"1267"} ,"907":{"x":116.0037,"y":40.3795,"region":"延庆县","Distribution":"15469"} ,"908":{"x":116.0037,"y":40.3995,"region":"延庆县","Distribution":"6116"} ,"909":{"x":116.0037,"y":40.4195,"region":"延庆县","Distribution":"63801"} ,"910":{"x":116.0037,"y":40.4395,"region":"延庆县","Distribution":"9114"} ,"911":{"x":116.0037,"y":40.4595,"region":"延庆县","Distribution":"2216"} ,"912":{"x":116.0037,"y":40.4795,"region":"延庆县","Distribution":"2326"} ,"913":{"x":116.0037,"y":40.4995,"region":"延庆县","Distribution":"11137"} ,"914":{"x":116.0037,"y":40.5195,"region":"延庆县","Distribution":"19639"} ,"915":{"x":116.0037,"y":40.5395,"region":"延庆县","Distribution":"3159"} ,"916":{"x":116.0037,"y":40.5595,"region":"延庆县","Distribution":"20358"} ,"954":{"x":116.0237,"y":40.3395,"region":"延庆县","Distribution":"24720"} ,"955":{"x":116.0237,"y":40.3595,"region":"延庆县","Distribution":"21490"} ,"956":{"x":116.0237,"y":40.3795,"region":"延庆县","Distribution":"34294"} ,"957":{"x":116.0237,"y":40.3995,"region":"延庆县","Distribution":"16649"} ,"958":{"x":116.0237,"y":40.4195,"region":"延庆县","Distribution":"14051"} ,"959":{"x":116.0237,"y":40.4395,"region":"延庆县","Distribution":"20072"} ,"960":{"x":116.0237,"y":40.4595,"region":"延庆县","Distribution":"2900"} ,"961":{"x":116.0237,"y":40.4795,"region":"延庆县","Distribution":"4138"} ,"962":{"x":116.0237,"y":40.4995,"region":"延庆县","Distribution":"10880"} ,"963":{"x":116.0237,"y":40.5195,"region":"延庆县","Distribution":"15976"} ,"964":{"x":116.0237,"y":40.5395,"region":"延庆县","Distribution":"52285"} ,"965":{"x":116.0237,"y":40.5595,"region":"延庆县","Distribution":"69084"} ,"966":{"x":116.0237,"y":40.5795,"region":"延庆县","Distribution":"58420"} ,"1004":{"x":116.0437,"y":40.3195,"region":"延庆县","Distribution":"607"} ,"1005":{"x":116.0437,"y":40.3395,"region":"延庆县","Distribution":"10276"} ,"1006":{"x":116.0437,"y":40.3595,"region":"延庆县","Distribution":"8937"} ,"1007":{"x":116.0437,"y":40.3795,"region":"延庆县","Distribution":"75"} ,"1008":{"x":116.0437,"y":40.3995,"region":"延庆县","Distribution":"5028"} ,"1009":{"x":116.0437,"y":40.4195,"region":"延庆县","Distribution":"8031"} ,"1010":{"x":116.0437,"y":40.4395,"region":"延庆县","Distribution":"46263"} ,"1011":{"x":116.0437,"y":40.4595,"region":"延庆县","Distribution":"45134"} ,"1012":{"x":116.0437,"y":40.4795,"region":"延庆县","Distribution":"11960"} ,"1013":{"x":116.0437,"y":40.4995,"region":"延庆县","Distribution":"232"} ,"1014":{"x":116.0437,"y":40.5195,"region":"延庆县","Distribution":"2198"} ,"1015":{"x":116.0437,"y":40.5395,"region":"延庆县","Distribution":"2557"} ,"1016":{"x":116.0437,"y":40.5595,"region":"延庆县","Distribution":"77133"} ,"1017":{"x":116.0437,"y":40.5795,"region":"延庆县","Distribution":"1404"} ,"1018":{"x":116.0437,"y":40.5995,"region":"延庆县","Distribution":"18051"} ,"1057":{"x":116.0637,"y":40.3395,"region":"延庆县","Distribution":"3071"} ,"1058":{"x":116.0637,"y":40.3595,"region":"延庆县","Distribution":"13962"} ,"1059":{"x":116.0637,"y":40.3795,"region":"延庆县","Distribution":"31229"} ,"1060":{"x":116.0637,"y":40.3995,"region":"延庆县","Distribution":"40614"} ,"1061":{"x":116.0637,"y":40.4195,"region":"延庆县","Distribution":"8534"} ,"1062":{"x":116.0637,"y":40.4395,"region":"延庆县","Distribution":"43921"} ,"1063":{"x":116.0637,"y":40.4595,"region":"延庆县","Distribution":"2087"} ,"1064":{"x":116.0637,"y":40.4795,"region":"延庆县","Distribution":"27276"} ,"1065":{"x":116.0637,"y":40.4995,"region":"延庆县","Distribution":"368"} ,"1066":{"x":116.0637,"y":40.5195,"region":"延庆县","Distribution":"62893"} ,"1067":{"x":116.0637,"y":40.5395,"region":"延庆县","Distribution":"2939"} ,"1068":{"x":116.0637,"y":40.5595,"region":"延庆县","Distribution":"139"} ,"1069":{"x":116.0637,"y":40.5795,"region":"延庆县","Distribution":"24588"} ,"1070":{"x":116.0637,"y":40.5995,"region":"延庆县","Distribution":"21237"} ,"1109":{"x":116.0837,"y":40.3395,"region":"延庆县","Distribution":"23271"} ,"1110":{"x":116.0837,"y":40.3595,"region":"延庆县","Distribution":"16087"} ,"1111":{"x":116.0837,"y":40.3795,"region":"延庆县","Distribution":"38867"} ,"1112":{"x":116.0837,"y":40.3995,"region":"延庆县","Distribution":"78320"} ,"1113":{"x":116.0837,"y":40.4195,"region":"延庆县","Distribution":"8079"} ,"1114":{"x":116.0837,"y":40.4395,"region":"延庆县","Distribution":"2849"} ,"1115":{"x":116.0837,"y":40.4595,"region":"延庆县","Distribution":"60462"} ,"1116":{"x":116.0837,"y":40.4795,"region":"延庆县","Distribution":"62545"} ,"1117":{"x":116.0837,"y":40.4995,"region":"延庆县","Distribution":"6575"} ,"1118":{"x":116.0837,"y":40.5195,"region":"延庆县","Distribution":"8912"} ,"1119":{"x":116.0837,"y":40.5395,"region":"延庆县","Distribution":"26685"} ,"1120":{"x":116.0837,"y":40.5595,"region":"延庆县","Distribution":"3797"} ,"1121":{"x":116.0837,"y":40.5795,"region":"延庆县","Distribution":"35034"} ,"1122":{"x":116.0837,"y":40.5995,"region":"延庆县","Distribution":"5518"} ,"1161":{"x":116.1037,"y":40.3395,"region":"延庆县","Distribution":"21678"} ,"1162":{"x":116.1037,"y":40.3595,"region":"延庆县","Distribution":"3827"} ,"1163":{"x":116.1037,"y":40.3795,"region":"延庆县","Distribution":"6970"} ,"1164":{"x":116.1037,"y":40.3995,"region":"延庆县","Distribution":"41646"} ,"1165":{"x":116.1037,"y":40.4195,"region":"延庆县","Distribution":"2690"} ,"1166":{"x":116.1037,"y":40.4395,"region":"延庆县","Distribution":"60294"} ,"1167":{"x":116.1037,"y":40.4595,"region":"延庆县","Distribution":"66504"} ,"1168":{"x":116.1037,"y":40.4795,"region":"延庆县","Distribution":"17317"} ,"1169":{"x":116.1037,"y":40.4995,"region":"延庆县","Distribution":"8333"} ,"1170":{"x":116.1037,"y":40.5195,"region":"延庆县","Distribution":"62310"} ,"1171":{"x":116.1037,"y":40.5395,"region":"延庆县","Distribution":"9601"} ,"1172":{"x":116.1037,"y":40.5595,"region":"延庆县","Distribution":"5395"} ,"1173":{"x":116.1037,"y":40.5795,"region":"延庆县","Distribution":"2361"} ,"1174":{"x":116.1037,"y":40.5995,"region":"延庆县","Distribution":"37946"} ,"1212":{"x":116.1237,"y":40.3195,"region":"延庆县","Distribution":"40504"} ,"1213":{"x":116.1237,"y":40.3395,"region":"延庆县","Distribution":"208"} ,"1214":{"x":116.1237,"y":40.3595,"region":"延庆县","Distribution":"545"} ,"1215":{"x":116.1237,"y":40.3795,"region":"延庆县","Distribution":"36010"} ,"1216":{"x":116.1237,"y":40.3995,"region":"延庆县","Distribution":"58258"} ,"1217":{"x":116.1237,"y":40.4195,"region":"延庆县","Distribution":"76404"} ,"1218":{"x":116.1237,"y":40.4395,"region":"延庆县","Distribution":"61910"} ,"1219":{"x":116.1237,"y":40.4595,"region":"延庆县","Distribution":"9831"} ,"1220":{"x":116.1237,"y":40.4795,"region":"延庆县","Distribution":"1994"} ,"1221":{"x":116.1237,"y":40.4995,"region":"延庆县","Distribution":"69391"} ,"1222":{"x":116.1237,"y":40.5195,"region":"延庆县","Distribution":"11165"} ,"1223":{"x":116.1237,"y":40.5395,"region":"延庆县","Distribution":"32561"} ,"1224":{"x":116.1237,"y":40.5595,"region":"延庆县","Distribution":"9648"} ,"1225":{"x":116.1237,"y":40.5795,"region":"延庆县","Distribution":"19229"} ,"1226":{"x":116.1237,"y":40.5995,"region":"延庆县","Distribution":"1219"} ,"1227":{"x":116.1237,"y":40.6195,"region":"延庆县","Distribution":"14116"} ,"1228":{"x":116.1237,"y":40.6395,"region":"延庆县","Distribution":"25018"} ,"1267":{"x":116.1437,"y":40.3395,"region":"延庆县","Distribution":"15824"} ,"1268":{"x":116.1437,"y":40.3595,"region":"延庆县","Distribution":"4293"} ,"1269":{"x":116.1437,"y":40.3795,"region":"延庆县","Distribution":"42182"} ,"1270":{"x":116.1437,"y":40.3995,"region":"延庆县","Distribution":"9127"} ,"1271":{"x":116.1437,"y":40.4195,"region":"延庆县","Distribution":"10804"} ,"1272":{"x":116.1437,"y":40.4395,"region":"延庆县","Distribution":"37136"} ,"1273":{"x":116.1437,"y":40.4595,"region":"延庆县","Distribution":"13473"} ,"1274":{"x":116.1437,"y":40.4795,"region":"延庆县","Distribution":"6124"} ,"1275":{"x":116.1437,"y":40.4995,"region":"延庆县","Distribution":"1190"} ,"1276":{"x":116.1437,"y":40.5195,"region":"延庆县","Distribution":"19656"} ,"1277":{"x":116.1437,"y":40.5395,"region":"延庆县","Distribution":"419"} ,"1278":{"x":116.1437,"y":40.5595,"region":"延庆县","Distribution":"29132"} ,"1279":{"x":116.1437,"y":40.5795,"region":"延庆县","Distribution":"25360"} ,"1280":{"x":116.1437,"y":40.5995,"region":"延庆县","Distribution":"39131"} ,"1281":{"x":116.1437,"y":40.6195,"region":"延庆县","Distribution":"29509"} ,"1282":{"x":116.1437,"y":40.6395,"region":"延庆县","Distribution":"23443"} ,"1283":{"x":116.1437,"y":40.6595,"region":"延庆县","Distribution":"7186"} ,"1323":{"x":116.1637,"y":40.3795,"region":"延庆县","Distribution":"47589"} ,"1324":{"x":116.1637,"y":40.3995,"region":"延庆县","Distribution":"1741"} ,"1325":{"x":116.1637,"y":40.4195,"region":"延庆县","Distribution":"3645"} ,"1326":{"x":116.1637,"y":40.4395,"region":"延庆县","Distribution":"38035"} ,"1327":{"x":116.1637,"y":40.4595,"region":"延庆县","Distribution":"37082"} ,"1328":{"x":116.1637,"y":40.4795,"region":"延庆县","Distribution":"37601"} ,"1329":{"x":116.1637,"y":40.4995,"region":"延庆县","Distribution":"25096"} ,"1330":{"x":116.1637,"y":40.5195,"region":"延庆县","Distribution":"12789"} ,"1331":{"x":116.1637,"y":40.5395,"region":"延庆县","Distribution":"50546"} ,"1332":{"x":116.1637,"y":40.5595,"region":"延庆县","Distribution":"33130"} ,"1333":{"x":116.1637,"y":40.5795,"region":"延庆县","Distribution":"24122"} ,"1334":{"x":116.1637,"y":40.5995,"region":"延庆县","Distribution":"29628"} ,"1335":{"x":116.1637,"y":40.6195,"region":"延庆县","Distribution":"9280"} ,"1336":{"x":116.1637,"y":40.6395,"region":"延庆县","Distribution":"3668"} ,"1337":{"x":116.1637,"y":40.6595,"region":"延庆县","Distribution":"3512"} ,"1377":{"x":116.1837,"y":40.3795,"region":"延庆县","Distribution":"14144"} ,"1378":{"x":116.1837,"y":40.3995,"region":"延庆县","Distribution":"13756"} ,"1379":{"x":116.1837,"y":40.4195,"region":"延庆县","Distribution":"30961"} ,"1380":{"x":116.1837,"y":40.4395,"region":"延庆县","Distribution":"6417"} ,"1381":{"x":116.1837,"y":40.4595,"region":"延庆县","Distribution":"30497"} ,"1382":{"x":116.1837,"y":40.4795,"region":"延庆县","Distribution":"48683"} ,"1383":{"x":116.1837,"y":40.4995,"region":"延庆县","Distribution":"28746"} ,"1384":{"x":116.1837,"y":40.5195,"region":"延庆县","Distribution":"6585"} ,"1385":{"x":116.1837,"y":40.5395,"region":"延庆县","Distribution":"3214"} ,"1386":{"x":116.1837,"y":40.5595,"region":"延庆县","Distribution":"53052"} ,"1387":{"x":116.1837,"y":40.5795,"region":"延庆县","Distribution":"2178"} ,"1388":{"x":116.1837,"y":40.5995,"region":"延庆县","Distribution":"57269"} ,"1389":{"x":116.1837,"y":40.6195,"region":"延庆县","Distribution":"35141"} ,"1390":{"x":116.1837,"y":40.6395,"region":"延庆县","Distribution":"26111"} ,"1391":{"x":116.1837,"y":40.6595,"region":"延庆县","Distribution":"26818"} ,"1392":{"x":116.1837,"y":40.6795,"region":"延庆县","Distribution":"20422"} ,"1393":{"x":116.1837,"y":40.6995,"region":"延庆县","Distribution":"38099"} ,"1434":{"x":116.2037,"y":40.3795,"region":"延庆县","Distribution":"33613"} ,"1435":{"x":116.2037,"y":40.3995,"region":"延庆县","Distribution":"43101"} ,"1436":{"x":116.2037,"y":40.4195,"region":"延庆县","Distribution":"25733"} ,"1437":{"x":116.2037,"y":40.4395,"region":"延庆县","Distribution":"7771"} ,"1438":{"x":116.2037,"y":40.4595,"region":"延庆县","Distribution":"27169"} ,"1439":{"x":116.2037,"y":40.4795,"region":"延庆县","Distribution":"2160"} ,"1440":{"x":116.2037,"y":40.4995,"region":"延庆县","Distribution":"45857"} ,"1441":{"x":116.2037,"y":40.5195,"region":"延庆县","Distribution":"64616"} ,"1442":{"x":116.2037,"y":40.5395,"region":"延庆县","Distribution":"31461"} ,"1443":{"x":116.2037,"y":40.5595,"region":"延庆县","Distribution":"21872"} ,"1444":{"x":116.2037,"y":40.5795,"region":"延庆县","Distribution":"12156"} ,"1445":{"x":116.2037,"y":40.5995,"region":"延庆县","Distribution":"1833"} ,"1446":{"x":116.2037,"y":40.6195,"region":"延庆县","Distribution":"3187"} ,"1447":{"x":116.2037,"y":40.6395,"region":"延庆县","Distribution":"73350"} ,"1448":{"x":116.2037,"y":40.6595,"region":"延庆县","Distribution":"25986"} ,"1449":{"x":116.2037,"y":40.6795,"region":"延庆县","Distribution":"14755"} ,"1450":{"x":116.2037,"y":40.6995,"region":"延庆县","Distribution":"25857"} ,"1492":{"x":116.2237,"y":40.3995,"region":"延庆县","Distribution":"75320"} ,"1493":{"x":116.2237,"y":40.4195,"region":"延庆县","Distribution":"49359"} ,"1494":{"x":116.2237,"y":40.4395,"region":"延庆县","Distribution":"66488"} ,"1495":{"x":116.2237,"y":40.4595,"region":"延庆县","Distribution":"40043"} ,"1496":{"x":116.2237,"y":40.4795,"region":"延庆县","Distribution":"14238"} ,"1497":{"x":116.2237,"y":40.4995,"region":"延庆县","Distribution":"74913"} ,"1498":{"x":116.2237,"y":40.5195,"region":"延庆县","Distribution":"48359"} ,"1499":{"x":116.2237,"y":40.5395,"region":"延庆县","Distribution":"5196"} ,"1500":{"x":116.2237,"y":40.5595,"region":"延庆县","Distribution":"62670"} ,"1501":{"x":116.2237,"y":40.5795,"region":"延庆县","Distribution":"22708"} ,"1502":{"x":116.2237,"y":40.5995,"region":"延庆县","Distribution":"18430"} ,"1503":{"x":116.2237,"y":40.6195,"region":"延庆县","Distribution":"34788"} ,"1504":{"x":116.2237,"y":40.6395,"region":"延庆县","Distribution":"2940"} ,"1505":{"x":116.2237,"y":40.6595,"region":"延庆县","Distribution":"28908"} ,"1506":{"x":116.2237,"y":40.6795,"region":"延庆县","Distribution":"74635"} ,"1507":{"x":116.2237,"y":40.6995,"region":"延庆县","Distribution":"255"} ,"1508":{"x":116.2237,"y":40.7195,"region":"延庆县","Distribution":"51347"} ,"1509":{"x":116.2237,"y":40.7395,"region":"延庆县","Distribution":"18893"} ,"1551":{"x":116.2437,"y":40.3795,"region":"延庆县","Distribution":"38364"} ,"1552":{"x":116.2437,"y":40.3995,"region":"延庆县","Distribution":"12117"} ,"1553":{"x":116.2437,"y":40.4195,"region":"延庆县","Distribution":"27769"} ,"1554":{"x":116.2437,"y":40.4395,"region":"延庆县","Distribution":"27692"} ,"1555":{"x":116.2437,"y":40.4595,"region":"延庆县","Distribution":"3274"} ,"1556":{"x":116.2437,"y":40.4795,"region":"延庆县","Distribution":"12861"} ,"1557":{"x":116.2437,"y":40.4995,"region":"延庆县","Distribution":"56292"} ,"1558":{"x":116.2437,"y":40.5195,"region":"延庆县","Distribution":"67354"} ,"1559":{"x":116.2437,"y":40.5395,"region":"延庆县","Distribution":"2501"} ,"1560":{"x":116.2437,"y":40.5595,"region":"延庆县","Distribution":"38177"} ,"1561":{"x":116.2437,"y":40.5795,"region":"延庆县","Distribution":"15192"} ,"1562":{"x":116.2437,"y":40.5995,"region":"延庆县","Distribution":"91783"} ,"1563":{"x":116.2437,"y":40.6195,"region":"延庆县","Distribution":"16223"} ,"1564":{"x":116.2437,"y":40.6395,"region":"延庆县","Distribution":"1690"} ,"1565":{"x":116.2437,"y":40.6595,"region":"延庆县","Distribution":"3209"} ,"1566":{"x":116.2437,"y":40.6795,"region":"延庆县","Distribution":"1135"} ,"1567":{"x":116.2437,"y":40.6995,"region":"延庆县","Distribution":"14701"} ,"1568":{"x":116.2437,"y":40.7195,"region":"延庆县","Distribution":"57329"} ,"1569":{"x":116.2437,"y":40.7395,"region":"延庆县","Distribution":"13909"} ,"1570":{"x":116.2437,"y":40.7595,"region":"延庆县","Distribution":"25376"} ,"1571":{"x":116.2437,"y":40.7795,"region":"延庆县","Distribution":"246"} ,"1616":{"x":116.2637,"y":40.3995,"region":"延庆县","Distribution":"1235"} ,"1617":{"x":116.2637,"y":40.4195,"region":"延庆县","Distribution":"15908"} ,"1618":{"x":116.2637,"y":40.4395,"region":"延庆县","Distribution":"10421"} ,"1619":{"x":116.2637,"y":40.4595,"region":"延庆县","Distribution":"6679"} ,"1620":{"x":116.2637,"y":40.4795,"region":"延庆县","Distribution":"38104"} ,"1621":{"x":116.2637,"y":40.4995,"region":"延庆县","Distribution":"14244"} ,"1622":{"x":116.2637,"y":40.5195,"region":"延庆县","Distribution":"4897"} ,"1623":{"x":116.2637,"y":40.5395,"region":"延庆县","Distribution":"5771"} ,"1624":{"x":116.2637,"y":40.5595,"region":"延庆县","Distribution":"11451"} ,"1625":{"x":116.2637,"y":40.5795,"region":"延庆县","Distribution":"32617"} ,"1626":{"x":116.2637,"y":40.5995,"region":"延庆县","Distribution":"77978"} ,"1627":{"x":116.2637,"y":40.6195,"region":"延庆县","Distribution":"40066"} ,"1628":{"x":116.2637,"y":40.6395,"region":"延庆县","Distribution":"16881"} ,"1629":{"x":116.2637,"y":40.6595,"region":"延庆县","Distribution":"9216"} ,"1630":{"x":116.2637,"y":40.6795,"region":"延庆县","Distribution":"8273"} ,"1631":{"x":116.2637,"y":40.6995,"region":"延庆县","Distribution":"6000"} ,"1632":{"x":116.2637,"y":40.7195,"region":"延庆县","Distribution":"4808"} ,"1633":{"x":116.2637,"y":40.7395,"region":"延庆县","Distribution":"11587"} ,"1634":{"x":116.2637,"y":40.7595,"region":"延庆县","Distribution":"61730"} ,"1635":{"x":116.2637,"y":40.7795,"region":"延庆县","Distribution":"4867"} ,"1680":{"x":116.2837,"y":40.3795,"region":"延庆县","Distribution":"1449"} ,"1681":{"x":116.2837,"y":40.3995,"region":"延庆县","Distribution":"16517"} ,"1682":{"x":116.2837,"y":40.4195,"region":"延庆县","Distribution":"5593"} ,"1683":{"x":116.2837,"y":40.4395,"region":"延庆县","Distribution":"49925"} ,"1684":{"x":116.2837,"y":40.4595,"region":"延庆县","Distribution":"57098"} ,"1685":{"x":116.2837,"y":40.4795,"region":"延庆县","Distribution":"6257"} ,"1686":{"x":116.2837,"y":40.4995,"region":"延庆县","Distribution":"4114"} ,"1687":{"x":116.2837,"y":40.5195,"region":"延庆县","Distribution":"9351"} ,"1688":{"x":116.2837,"y":40.5395,"region":"延庆县","Distribution":"4094"} ,"1689":{"x":116.2837,"y":40.5595,"region":"延庆县","Distribution":"27023"} ,"1690":{"x":116.2837,"y":40.5795,"region":"延庆县","Distribution":"76959"} ,"1691":{"x":116.2837,"y":40.5995,"region":"延庆县","Distribution":"15654"} ,"1692":{"x":116.2837,"y":40.6195,"region":"延庆县","Distribution":"68706"} ,"1693":{"x":116.2837,"y":40.6395,"region":"延庆县","Distribution":"28834"} ,"1694":{"x":116.2837,"y":40.6595,"region":"延庆县","Distribution":"10840"} ,"1695":{"x":116.2837,"y":40.6795,"region":"延庆县","Distribution":"22545"} ,"1696":{"x":116.2837,"y":40.6995,"region":"延庆县","Distribution":"7917"} ,"1697":{"x":116.2837,"y":40.7195,"region":"延庆县","Distribution":"23806"} ,"1698":{"x":116.2837,"y":40.7395,"region":"延庆县","Distribution":"2328"} ,"1699":{"x":116.2837,"y":40.7595,"region":"延庆县","Distribution":"25851"} ,"1750":{"x":116.3037,"y":40.4995,"region":"延庆县","Distribution":"2432"} ,"1751":{"x":116.3037,"y":40.5195,"region":"延庆县","Distribution":"16357"} ,"1752":{"x":116.3037,"y":40.5395,"region":"延庆县","Distribution":"2607"} ,"1753":{"x":116.3037,"y":40.5595,"region":"延庆县","Distribution":"4997"} ,"1754":{"x":116.3037,"y":40.5795,"region":"延庆县","Distribution":"16590"} ,"1755":{"x":116.3037,"y":40.5995,"region":"延庆县","Distribution":"9094"} ,"1756":{"x":116.3037,"y":40.6195,"region":"延庆县","Distribution":"52715"} ,"1757":{"x":116.3037,"y":40.6395,"region":"延庆县","Distribution":"45964"} ,"1758":{"x":116.3037,"y":40.6595,"region":"延庆县","Distribution":"4820"} ,"1759":{"x":116.3037,"y":40.6795,"region":"延庆县","Distribution":"4706"} ,"1760":{"x":116.3037,"y":40.6995,"region":"延庆县","Distribution":"60060"} ,"1761":{"x":116.3037,"y":40.7195,"region":"延庆县","Distribution":"51038"} ,"1762":{"x":116.3037,"y":40.7395,"region":"延庆县","Distribution":"188"} ,"1814":{"x":116.3237,"y":40.4995,"region":"延庆县","Distribution":"39035"} ,"1815":{"x":116.3237,"y":40.5195,"region":"延庆县","Distribution":"30141"} ,"1816":{"x":116.3237,"y":40.5395,"region":"延庆县","Distribution":"33509"} ,"1817":{"x":116.3237,"y":40.5595,"region":"延庆县","Distribution":"8766"} ,"1818":{"x":116.3237,"y":40.5795,"region":"延庆县","Distribution":"20381"} ,"1819":{"x":116.3237,"y":40.5995,"region":"延庆县","Distribution":"7769"} ,"1820":{"x":116.3237,"y":40.6195,"region":"延庆县","Distribution":"63550"} ,"1821":{"x":116.3237,"y":40.6395,"region":"延庆县","Distribution":"8832"} ,"1822":{"x":116.3237,"y":40.6595,"region":"延庆县","Distribution":"8021"} ,"1823":{"x":116.3237,"y":40.6795,"region":"延庆县","Distribution":"26879"} ,"1824":{"x":116.3237,"y":40.6995,"region":"延庆县","Distribution":"55584"} ,"1825":{"x":116.3237,"y":40.7195,"region":"延庆县","Distribution":"2224"} ,"1826":{"x":116.3237,"y":40.7395,"region":"延庆县","Distribution":"15730"} ,"1827":{"x":116.3237,"y":40.7595,"region":"延庆县","Distribution":"6722"} ,"1881":{"x":116.3437,"y":40.5195,"region":"延庆县","Distribution":"49070"} ,"1882":{"x":116.3437,"y":40.5395,"region":"延庆县","Distribution":"7639"} ,"1883":{"x":116.3437,"y":40.5595,"region":"延庆县","Distribution":"36849"} ,"1884":{"x":116.3437,"y":40.5795,"region":"延庆县","Distribution":"44316"} ,"1885":{"x":116.3437,"y":40.5995,"region":"延庆县","Distribution":"21733"} ,"1886":{"x":116.3437,"y":40.6195,"region":"延庆县","Distribution":"29307"} ,"1887":{"x":116.3437,"y":40.6395,"region":"延庆县","Distribution":"7356"} ,"1888":{"x":116.3437,"y":40.6595,"region":"延庆县","Distribution":"31448"} ,"1889":{"x":116.3437,"y":40.6795,"region":"延庆县","Distribution":"49021"} ,"1890":{"x":116.3437,"y":40.6995,"region":"延庆县","Distribution":"25734"} ,"1891":{"x":116.3437,"y":40.7195,"region":"延庆县","Distribution":"31428"} ,"1892":{"x":116.3437,"y":40.7395,"region":"延庆县","Distribution":"28735"} ,"1893":{"x":116.3437,"y":40.7595,"region":"延庆县","Distribution":"3834"} ,"1948":{"x":116.3637,"y":40.5195,"region":"延庆县","Distribution":"50642"} ,"1949":{"x":116.3637,"y":40.5395,"region":"延庆县","Distribution":"38244"} ,"1950":{"x":116.3637,"y":40.5595,"region":"延庆县","Distribution":"63152"} ,"1951":{"x":116.3637,"y":40.5795,"region":"延庆县","Distribution":"87789"} ,"1952":{"x":116.3637,"y":40.5995,"region":"延庆县","Distribution":"2297"} ,"1953":{"x":116.3637,"y":40.6195,"region":"延庆县","Distribution":"24331"} ,"1954":{"x":116.3637,"y":40.6395,"region":"延庆县","Distribution":"2628"} ,"1955":{"x":116.3637,"y":40.6595,"region":"延庆县","Distribution":"26101"} ,"1956":{"x":116.3637,"y":40.6795,"region":"延庆县","Distribution":"89389"} ,"1957":{"x":116.3637,"y":40.6995,"region":"延庆县","Distribution":"14230"} ,"1958":{"x":116.3637,"y":40.7195,"region":"延庆县","Distribution":"10674"} ,"1959":{"x":116.3637,"y":40.7395,"region":"延庆县","Distribution":"20080"} ,"1960":{"x":116.3637,"y":40.7595,"region":"延庆县","Distribution":"5198"} ,"2013":{"x":116.3837,"y":40.4995,"region":"延庆县","Distribution":"5122"} ,"2014":{"x":116.3837,"y":40.5195,"region":"延庆县","Distribution":"7681"} ,"2015":{"x":116.3837,"y":40.5395,"region":"延庆县","Distribution":"11528"} ,"2016":{"x":116.3837,"y":40.5595,"region":"延庆县","Distribution":"65636"} ,"2017":{"x":116.3837,"y":40.5795,"region":"延庆县","Distribution":"77140"} ,"2018":{"x":116.3837,"y":40.5995,"region":"延庆县","Distribution":"11997"} ,"2019":{"x":116.3837,"y":40.6195,"region":"延庆县","Distribution":"3044"} ,"2020":{"x":116.3837,"y":40.6395,"region":"延庆县","Distribution":"14944"} ,"2021":{"x":116.3837,"y":40.6595,"region":"延庆县","Distribution":"50944"} ,"2022":{"x":116.3837,"y":40.6795,"region":"延庆县","Distribution":"30630"} ,"2023":{"x":116.3837,"y":40.6995,"region":"延庆县","Distribution":"33468"} ,"2024":{"x":116.3837,"y":40.7195,"region":"延庆县","Distribution":"34097"} ,"2025":{"x":116.3837,"y":40.7395,"region":"延庆县","Distribution":"43630"} ,"2026":{"x":116.3837,"y":40.7595,"region":"延庆县","Distribution":"30201"} ,"2078":{"x":116.4037,"y":40.4995,"region":"延庆县","Distribution":"21801"} ,"2079":{"x":116.4037,"y":40.5195,"region":"延庆县","Distribution":"24304"} ,"2080":{"x":116.4037,"y":40.5395,"region":"延庆县","Distribution":"25318"} ,"2081":{"x":116.4037,"y":40.5595,"region":"延庆县","Distribution":"4347"} ,"2082":{"x":116.4037,"y":40.5795,"region":"延庆县","Distribution":"6125"} ,"2083":{"x":116.4037,"y":40.5995,"region":"延庆县","Distribution":"21683"} ,"2084":{"x":116.4037,"y":40.6195,"region":"延庆县","Distribution":"12507"} ,"2085":{"x":116.4037,"y":40.6395,"region":"延庆县","Distribution":"19407"} ,"2086":{"x":116.4037,"y":40.6595,"region":"延庆县","Distribution":"670"} ,"2087":{"x":116.4037,"y":40.6795,"region":"延庆县","Distribution":"28588"} ,"2088":{"x":116.4037,"y":40.6995,"region":"延庆县","Distribution":"66847"} ,"2089":{"x":116.4037,"y":40.7195,"region":"延庆县","Distribution":"10881"} ,"2090":{"x":116.4037,"y":40.7395,"region":"延庆县","Distribution":"33321"} ,"2091":{"x":116.4037,"y":40.7595,"region":"延庆县","Distribution":"11131"} ,"2141":{"x":116.4237,"y":40.4995,"region":"延庆县","Distribution":"61580"} ,"2142":{"x":116.4237,"y":40.5195,"region":"延庆县","Distribution":"45309"} ,"2143":{"x":116.4237,"y":40.5395,"region":"延庆县","Distribution":"28428"} ,"2144":{"x":116.4237,"y":40.5595,"region":"延庆县","Distribution":"39213"} ,"2145":{"x":116.4237,"y":40.5795,"region":"延庆县","Distribution":"4134"} ,"2146":{"x":116.4237,"y":40.5995,"region":"延庆县","Distribution":"38132"} ,"2147":{"x":116.4237,"y":40.6195,"region":"延庆县","Distribution":"58143"} ,"2148":{"x":116.4237,"y":40.6395,"region":"延庆县","Distribution":"7091"} ,"2149":{"x":116.4237,"y":40.6595,"region":"延庆县","Distribution":"9537"} ,"2150":{"x":116.4237,"y":40.6795,"region":"延庆县","Distribution":"11887"} ,"2151":{"x":116.4237,"y":40.6995,"region":"延庆县","Distribution":"27396"} ,"2152":{"x":116.4237,"y":40.7195,"region":"延庆县","Distribution":"11951"} ,"2153":{"x":116.4237,"y":40.7395,"region":"延庆县","Distribution":"15518"} ,"2154":{"x":116.4237,"y":40.7595,"region":"延庆县","Distribution":"49946"} ,"2201":{"x":116.4437,"y":40.4995,"region":"延庆县","Distribution":"63696"} ,"2202":{"x":116.4437,"y":40.5195,"region":"延庆县","Distribution":"982"} ,"2203":{"x":116.4437,"y":40.5395,"region":"延庆县","Distribution":"48806"} ,"2204":{"x":116.4437,"y":40.5595,"region":"延庆县","Distribution":"75582"} ,"2205":{"x":116.4437,"y":40.5795,"region":"延庆县","Distribution":"23407"} ,"2206":{"x":116.4437,"y":40.5995,"region":"延庆县","Distribution":"18873"} ,"2207":{"x":116.4437,"y":40.6195,"region":"延庆县","Distribution":"12613"} ,"2208":{"x":116.4437,"y":40.6395,"region":"延庆县","Distribution":"11879"} ,"2209":{"x":116.4437,"y":40.6595,"region":"延庆县","Distribution":"30887"} ,"2210":{"x":116.4437,"y":40.6795,"region":"延庆县","Distribution":"62696"} ,"2211":{"x":116.4437,"y":40.6995,"region":"延庆县","Distribution":"43146"} ,"2212":{"x":116.4437,"y":40.7195,"region":"延庆县","Distribution":"12775"} ,"2213":{"x":116.4437,"y":40.7395,"region":"延庆县","Distribution":"32801"} ,"2214":{"x":116.4437,"y":40.7595,"region":"延庆县","Distribution":"5232"} ,"2254":{"x":116.4637,"y":40.4995,"region":"延庆县","Distribution":"7288"} ,"2255":{"x":116.4637,"y":40.5195,"region":"延庆县","Distribution":"39746"} ,"2256":{"x":116.4637,"y":40.5395,"region":"延庆县","Distribution":"5053"} ,"2257":{"x":116.4637,"y":40.5595,"region":"延庆县","Distribution":"61109"} ,"2258":{"x":116.4637,"y":40.5795,"region":"延庆县","Distribution":"63412"} ,"2259":{"x":116.4637,"y":40.5995,"region":"延庆县","Distribution":"33366"} ,"2260":{"x":116.4637,"y":40.6195,"region":"延庆县","Distribution":"16043"} ,"2261":{"x":116.4637,"y":40.6395,"region":"延庆县","Distribution":"28229"} ,"2262":{"x":116.4637,"y":40.6595,"region":"延庆县","Distribution":"54495"} ,"2263":{"x":116.4637,"y":40.6795,"region":"延庆县","Distribution":"14056"} ,"2264":{"x":116.4637,"y":40.6995,"region":"延庆县","Distribution":"57553"} ,"2265":{"x":116.4637,"y":40.7195,"region":"延庆县","Distribution":"4447"} ,"2266":{"x":116.4637,"y":40.7395,"region":"延庆县","Distribution":"79393"} ,"2267":{"x":116.4637,"y":40.7595,"region":"延庆县","Distribution":"26529"} ,"2307":{"x":116.4837,"y":40.4995,"region":"延庆县","Distribution":"2223"} ,"2310":{"x":116.4837,"y":40.5595,"region":"延庆县","Distribution":"1211"} ,"2311":{"x":116.4837,"y":40.5795,"region":"延庆县","Distribution":"22551"} ,"2312":{"x":116.4837,"y":40.5995,"region":"延庆县","Distribution":"10157"} ,"2313":{"x":116.4837,"y":40.6195,"region":"延庆县","Distribution":"8672"} ,"2314":{"x":116.4837,"y":40.6395,"region":"延庆县","Distribution":"827"} ,"2315":{"x":116.4837,"y":40.6595,"region":"延庆县","Distribution":"8984"} ,"2316":{"x":116.4837,"y":40.6795,"region":"延庆县","Distribution":"45849"} ,"2317":{"x":116.4837,"y":40.6995,"region":"延庆县","Distribution":"7317"} ,"2318":{"x":116.4837,"y":40.7195,"region":"延庆县","Distribution":"6442"} ,"2319":{"x":116.4837,"y":40.7395,"region":"延庆县","Distribution":"9184"} ,"2320":{"x":116.4837,"y":40.7595,"region":"延庆县","Distribution":"7475"} ,"2357":{"x":116.5037,"y":40.4995,"region":"延庆县","Distribution":"12074"} ,"2361":{"x":116.5037,"y":40.5795,"region":"延庆县","Distribution":"21481"} ,"2362":{"x":116.5037,"y":40.5995,"region":"延庆县","Distribution":"1402"} ,"2363":{"x":116.5037,"y":40.6195,"region":"延庆县","Distribution":"25267"} ,"2364":{"x":116.5037,"y":40.6395,"region":"延庆县","Distribution":"53734"} ,"2365":{"x":116.5037,"y":40.6595,"region":"延庆县","Distribution":"3004"} ,"2368":{"x":116.5037,"y":40.7195,"region":"延庆县","Distribution":"8882"} ,"2369":{"x":116.5037,"y":40.7395,"region":"延庆县","Distribution":"13345"} ,"2410":{"x":116.5237,"y":40.5995,"region":"延庆县","Distribution":"17227"} ,"2411":{"x":116.5237,"y":40.6195,"region":"延庆县","Distribution":"38552"} ,"2412":{"x":116.5237,"y":40.6395,"region":"延庆县","Distribution":"78679"} ,"2460":{"x":116.5437,"y":40.6395,"region":"延庆县","Distribution":"20102"} }}]