[{"id":"昌平区","amount":{"568":{"x":115.8637,"y":40.1595,"region":"昌平区","Distribution":"79141"} ,"569":{"x":115.8637,"y":40.1795,"region":"昌平区","Distribution":"75498"} ,"611":{"x":115.8837,"y":40.1595,"region":"昌平区","Distribution":"2947"} ,"612":{"x":115.8837,"y":40.1795,"region":"昌平区","Distribution":"38382"} ,"613":{"x":115.8837,"y":40.1995,"region":"昌平区","Distribution":"2236"} ,"653":{"x":115.9037,"y":40.1395,"region":"昌平区","Distribution":"49738"} ,"654":{"x":115.9037,"y":40.1595,"region":"昌平区","Distribution":"1565"} ,"655":{"x":115.9037,"y":40.1795,"region":"昌平区","Distribution":"15486"} ,"656":{"x":115.9037,"y":40.1995,"region":"昌平区","Distribution":"55346"} ,"657":{"x":115.9037,"y":40.2195,"region":"昌平区","Distribution":"666"} ,"696":{"x":115.9237,"y":40.1195,"region":"昌平区","Distribution":"66440"} ,"697":{"x":115.9237,"y":40.1395,"region":"昌平区","Distribution":"1065"} ,"698":{"x":115.9237,"y":40.1595,"region":"昌平区","Distribution":"43358"} ,"699":{"x":115.9237,"y":40.1795,"region":"昌平区","Distribution":"812"} ,"700":{"x":115.9237,"y":40.1995,"region":"昌平区","Distribution":"931"} ,"701":{"x":115.9237,"y":40.2195,"region":"昌平区","Distribution":"3073"} ,"702":{"x":115.9237,"y":40.2395,"region":"昌平区","Distribution":"4332"} ,"744":{"x":115.9437,"y":40.1195,"region":"昌平区","Distribution":"48036"} ,"745":{"x":115.9437,"y":40.1395,"region":"昌平区","Distribution":"23082"} ,"746":{"x":115.9437,"y":40.1595,"region":"昌平区","Distribution":"522"} ,"747":{"x":115.9437,"y":40.1795,"region":"昌平区","Distribution":"13311"} ,"748":{"x":115.9437,"y":40.1995,"region":"昌平区","Distribution":"1917"} ,"749":{"x":115.9437,"y":40.2195,"region":"昌平区","Distribution":"15691"} ,"750":{"x":115.9437,"y":40.2395,"region":"昌平区","Distribution":"7282"} ,"793":{"x":115.9637,"y":40.0995,"region":"昌平区","Distribution":"1812"} ,"794":{"x":115.9637,"y":40.1195,"region":"昌平区","Distribution":"4126"} ,"795":{"x":115.9637,"y":40.1395,"region":"昌平区","Distribution":"1267"} ,"796":{"x":115.9637,"y":40.1595,"region":"昌平区","Distribution":"2004"} ,"797":{"x":115.9637,"y":40.1795,"region":"昌平区","Distribution":"29142"} ,"798":{"x":115.9637,"y":40.1995,"region":"昌平区","Distribution":"44663"} ,"799":{"x":115.9637,"y":40.2195,"region":"昌平区","Distribution":"15985"} ,"800":{"x":115.9637,"y":40.2395,"region":"昌平区","Distribution":"27359"} ,"843":{"x":115.9837,"y":40.0995,"region":"昌平区","Distribution":"44095"} ,"844":{"x":115.9837,"y":40.1195,"region":"昌平区","Distribution":"35701"} ,"845":{"x":115.9837,"y":40.1395,"region":"昌平区","Distribution":"16301"} ,"846":{"x":115.9837,"y":40.1595,"region":"昌平区","Distribution":"5661"} ,"847":{"x":115.9837,"y":40.1795,"region":"昌平区","Distribution":"6930"} ,"848":{"x":115.9837,"y":40.1995,"region":"昌平区","Distribution":"27160"} ,"849":{"x":115.9837,"y":40.2195,"region":"昌平区","Distribution":"11534"} ,"850":{"x":115.9837,"y":40.2395,"region":"昌平区","Distribution":"20531"} ,"851":{"x":115.9837,"y":40.2595,"region":"昌平区","Distribution":"19321"} ,"852":{"x":115.9837,"y":40.2795,"region":"昌平区","Distribution":"42193"} ,"854":{"x":115.9837,"y":40.3195,"region":"昌平区","Distribution":"16245"} ,"893":{"x":116.0037,"y":40.0995,"region":"昌平区","Distribution":"9245"} ,"894":{"x":116.0037,"y":40.1195,"region":"昌平区","Distribution":"55139"} ,"895":{"x":116.0037,"y":40.1395,"region":"昌平区","Distribution":"23990"} ,"896":{"x":116.0037,"y":40.1595,"region":"昌平区","Distribution":"30783"} ,"897":{"x":116.0037,"y":40.1795,"region":"昌平区","Distribution":"1372"} ,"898":{"x":116.0037,"y":40.1995,"region":"昌平区","Distribution":"1103"} ,"899":{"x":116.0037,"y":40.2195,"region":"昌平区","Distribution":"70616"} ,"900":{"x":116.0037,"y":40.2395,"region":"昌平区","Distribution":"47832"} ,"901":{"x":116.0037,"y":40.2595,"region":"昌平区","Distribution":"28534"} ,"902":{"x":116.0037,"y":40.2795,"region":"昌平区","Distribution":"8339"} ,"903":{"x":116.0037,"y":40.2995,"region":"昌平区","Distribution":"31847"} ,"904":{"x":116.0037,"y":40.3195,"region":"昌平区","Distribution":"4033"} ,"941":{"x":116.0237,"y":40.0795,"region":"昌平区","Distribution":"604"} ,"942":{"x":116.0237,"y":40.0995,"region":"昌平区","Distribution":"4306"} ,"943":{"x":116.0237,"y":40.1195,"region":"昌平区","Distribution":"64411"} ,"944":{"x":116.0237,"y":40.1395,"region":"昌平区","Distribution":"1060"} ,"945":{"x":116.0237,"y":40.1595,"region":"昌平区","Distribution":"49335"} ,"946":{"x":116.0237,"y":40.1795,"region":"昌平区","Distribution":"4979"} ,"947":{"x":116.0237,"y":40.1995,"region":"昌平区","Distribution":"9213"} ,"948":{"x":116.0237,"y":40.2195,"region":"昌平区","Distribution":"13483"} ,"949":{"x":116.0237,"y":40.2395,"region":"昌平区","Distribution":"6943"} ,"950":{"x":116.0237,"y":40.2595,"region":"昌平区","Distribution":"7075"} ,"951":{"x":116.0237,"y":40.2795,"region":"昌平区","Distribution":"10114"} ,"952":{"x":116.0237,"y":40.2995,"region":"昌平区","Distribution":"46739"} ,"953":{"x":116.0237,"y":40.3195,"region":"昌平区","Distribution":"15601"} ,"993":{"x":116.0437,"y":40.0995,"region":"昌平区","Distribution":"33065"} ,"994":{"x":116.0437,"y":40.1195,"region":"昌平区","Distribution":"47176"} ,"995":{"x":116.0437,"y":40.1395,"region":"昌平区","Distribution":"6585"} ,"996":{"x":116.0437,"y":40.1595,"region":"昌平区","Distribution":"22500"} ,"997":{"x":116.0437,"y":40.1795,"region":"昌平区","Distribution":"44611"} ,"998":{"x":116.0437,"y":40.1995,"region":"昌平区","Distribution":"3815"} ,"999":{"x":116.0437,"y":40.2195,"region":"昌平区","Distribution":"10051"} ,"1000":{"x":116.0437,"y":40.2395,"region":"昌平区","Distribution":"35947"} ,"1001":{"x":116.0437,"y":40.2595,"region":"昌平区","Distribution":"16574"} ,"1002":{"x":116.0437,"y":40.2795,"region":"昌平区","Distribution":"55919"} ,"1003":{"x":116.0437,"y":40.2995,"region":"昌平区","Distribution":"303"} ,"1046":{"x":116.0637,"y":40.1195,"region":"昌平区","Distribution":"3768"} ,"1047":{"x":116.0637,"y":40.1395,"region":"昌平区","Distribution":"36206"} ,"1048":{"x":116.0637,"y":40.1595,"region":"昌平区","Distribution":"81308"} ,"1049":{"x":116.0637,"y":40.1795,"region":"昌平区","Distribution":"3094"} ,"1050":{"x":116.0637,"y":40.1995,"region":"昌平区","Distribution":"61983"} ,"1051":{"x":116.0637,"y":40.2195,"region":"昌平区","Distribution":"13876"} ,"1052":{"x":116.0637,"y":40.2395,"region":"昌平区","Distribution":"2209"} ,"1053":{"x":116.0637,"y":40.2595,"region":"昌平区","Distribution":"2741"} ,"1054":{"x":116.0637,"y":40.2795,"region":"昌平区","Distribution":"9531"} ,"1055":{"x":116.0637,"y":40.2995,"region":"昌平区","Distribution":"12351"} ,"1056":{"x":116.0637,"y":40.3195,"region":"昌平区","Distribution":"47841"} ,"1098":{"x":116.0837,"y":40.1195,"region":"昌平区","Distribution":"8484"} ,"1099":{"x":116.0837,"y":40.1395,"region":"昌平区","Distribution":"43804"} ,"1100":{"x":116.0837,"y":40.1595,"region":"昌平区","Distribution":"50962"} ,"1101":{"x":116.0837,"y":40.1795,"region":"昌平区","Distribution":"1171"} ,"1102":{"x":116.0837,"y":40.1995,"region":"昌平区","Distribution":"43746"} ,"1103":{"x":116.0837,"y":40.2195,"region":"昌平区","Distribution":"29668"} ,"1104":{"x":116.0837,"y":40.2395,"region":"昌平区","Distribution":"22469"} ,"1105":{"x":116.0837,"y":40.2595,"region":"昌平区","Distribution":"49105"} ,"1106":{"x":116.0837,"y":40.2795,"region":"昌平区","Distribution":"22338"} ,"1107":{"x":116.0837,"y":40.2995,"region":"昌平区","Distribution":"49119"} ,"1108":{"x":116.0837,"y":40.3195,"region":"昌平区","Distribution":"2116"} ,"1150":{"x":116.1037,"y":40.1195,"region":"昌平区","Distribution":"15324"} ,"1151":{"x":116.1037,"y":40.1395,"region":"昌平区","Distribution":"57"} ,"1152":{"x":116.1037,"y":40.1595,"region":"昌平区","Distribution":"79989"} ,"1153":{"x":116.1037,"y":40.1795,"region":"昌平区","Distribution":"16924"} ,"1154":{"x":116.1037,"y":40.1995,"region":"昌平区","Distribution":"2908"} ,"1155":{"x":116.1037,"y":40.2195,"region":"昌平区","Distribution":"18704"} ,"1156":{"x":116.1037,"y":40.2395,"region":"昌平区","Distribution":"33326"} ,"1157":{"x":116.1037,"y":40.2595,"region":"昌平区","Distribution":"25061"} ,"1158":{"x":116.1037,"y":40.2795,"region":"昌平区","Distribution":"2090"} ,"1159":{"x":116.1037,"y":40.2995,"region":"昌平区","Distribution":"23608"} ,"1160":{"x":116.1037,"y":40.3195,"region":"昌平区","Distribution":"51794"} ,"1202":{"x":116.1237,"y":40.1195,"region":"昌平区","Distribution":"24022"} ,"1203":{"x":116.1237,"y":40.1395,"region":"昌平区","Distribution":"20160"} ,"1204":{"x":116.1237,"y":40.1595,"region":"昌平区","Distribution":"1139"} ,"1205":{"x":116.1237,"y":40.1795,"region":"昌平区","Distribution":"15956"} ,"1206":{"x":116.1237,"y":40.1995,"region":"昌平区","Distribution":"2292"} ,"1207":{"x":116.1237,"y":40.2195,"region":"昌平区","Distribution":"72910"} ,"1208":{"x":116.1237,"y":40.2395,"region":"昌平区","Distribution":"5451"} ,"1209":{"x":116.1237,"y":40.2595,"region":"昌平区","Distribution":"79"} ,"1210":{"x":116.1237,"y":40.2795,"region":"昌平区","Distribution":"14003"} ,"1211":{"x":116.1237,"y":40.2995,"region":"昌平区","Distribution":"15"} ,"1257":{"x":116.1437,"y":40.1395,"region":"昌平区","Distribution":"368"} ,"1258":{"x":116.1437,"y":40.1595,"region":"昌平区","Distribution":"38542"} ,"1259":{"x":116.1437,"y":40.1795,"region":"昌平区","Distribution":"31541"} ,"1260":{"x":116.1437,"y":40.1995,"region":"昌平区","Distribution":"2776"} ,"1261":{"x":116.1437,"y":40.2195,"region":"昌平区","Distribution":"18034"} ,"1262":{"x":116.1437,"y":40.2395,"region":"昌平区","Distribution":"510"} ,"1263":{"x":116.1437,"y":40.2595,"region":"昌平区","Distribution":"66776"} ,"1264":{"x":116.1437,"y":40.2795,"region":"昌平区","Distribution":"17699"} ,"1265":{"x":116.1437,"y":40.2995,"region":"昌平区","Distribution":"6093"} ,"1266":{"x":116.1437,"y":40.3195,"region":"昌平区","Distribution":"70229"} ,"1311":{"x":116.1637,"y":40.1395,"region":"昌平区","Distribution":"6014"} ,"1312":{"x":116.1637,"y":40.1595,"region":"昌平区","Distribution":"71943"} ,"1313":{"x":116.1637,"y":40.1795,"region":"昌平区","Distribution":"5731"} ,"1314":{"x":116.1637,"y":40.1995,"region":"昌平区","Distribution":"12062"} ,"1315":{"x":116.1637,"y":40.2195,"region":"昌平区","Distribution":"12886"} ,"1316":{"x":116.1637,"y":40.2395,"region":"昌平区","Distribution":"43021"} ,"1317":{"x":116.1637,"y":40.2595,"region":"昌平区","Distribution":"3448"} ,"1318":{"x":116.1637,"y":40.2795,"region":"昌平区","Distribution":"15523"} ,"1319":{"x":116.1637,"y":40.2995,"region":"昌平区","Distribution":"21409"} ,"1320":{"x":116.1637,"y":40.3195,"region":"昌平区","Distribution":"653"} ,"1321":{"x":116.1637,"y":40.3395,"region":"昌平区","Distribution":"24110"} ,"1322":{"x":116.1637,"y":40.3595,"region":"昌平区","Distribution":"31273"} ,"1366":{"x":116.1837,"y":40.1595,"region":"昌平区","Distribution":"61689"} ,"1367":{"x":116.1837,"y":40.1795,"region":"昌平区","Distribution":"5597"} ,"1368":{"x":116.1837,"y":40.1995,"region":"昌平区","Distribution":"44924"} ,"1369":{"x":116.1837,"y":40.2195,"region":"昌平区","Distribution":"24706"} ,"1370":{"x":116.1837,"y":40.2395,"region":"昌平区","Distribution":"13849"} ,"1371":{"x":116.1837,"y":40.2595,"region":"昌平区","Distribution":"34758"} ,"1372":{"x":116.1837,"y":40.2795,"region":"昌平区","Distribution":"10152"} ,"1373":{"x":116.1837,"y":40.2995,"region":"昌平区","Distribution":"27518"} ,"1374":{"x":116.1837,"y":40.3195,"region":"昌平区","Distribution":"57169"} ,"1375":{"x":116.1837,"y":40.3395,"region":"昌平区","Distribution":"10549"} ,"1376":{"x":116.1837,"y":40.3595,"region":"昌平区","Distribution":"2429"} ,"1423":{"x":116.2037,"y":40.1595,"region":"昌平区","Distribution":"21226"} ,"1424":{"x":116.2037,"y":40.1795,"region":"昌平区","Distribution":"58192"} ,"1425":{"x":116.2037,"y":40.1995,"region":"昌平区","Distribution":"31454"} ,"1426":{"x":116.2037,"y":40.2195,"region":"昌平区","Distribution":"3219"} ,"1427":{"x":116.2037,"y":40.2395,"region":"昌平区","Distribution":"65678"} ,"1428":{"x":116.2037,"y":40.2595,"region":"昌平区","Distribution":"67948"} ,"1429":{"x":116.2037,"y":40.2795,"region":"昌平区","Distribution":"32590"} ,"1430":{"x":116.2037,"y":40.2995,"region":"昌平区","Distribution":"7248"} ,"1431":{"x":116.2037,"y":40.3195,"region":"昌平区","Distribution":"27238"} ,"1432":{"x":116.2037,"y":40.3395,"region":"昌平区","Distribution":"28849"} ,"1433":{"x":116.2037,"y":40.3595,"region":"昌平区","Distribution":"32597"} ,"1479":{"x":116.2237,"y":40.1395,"region":"昌平区","Distribution":"47973"} ,"1480":{"x":116.2237,"y":40.1595,"region":"昌平区","Distribution":"21298"} ,"1481":{"x":116.2237,"y":40.1795,"region":"昌平区","Distribution":"26069"} ,"1482":{"x":116.2237,"y":40.1995,"region":"昌平区","Distribution":"39149"} ,"1483":{"x":116.2237,"y":40.2195,"region":"昌平区","Distribution":"58086"} ,"1484":{"x":116.2237,"y":40.2395,"region":"昌平区","Distribution":"20474"} ,"1485":{"x":116.2237,"y":40.2595,"region":"昌平区","Distribution":"56545"} ,"1486":{"x":116.2237,"y":40.2795,"region":"昌平区","Distribution":"8242"} ,"1487":{"x":116.2237,"y":40.2995,"region":"昌平区","Distribution":"1404"} ,"1488":{"x":116.2237,"y":40.3195,"region":"昌平区","Distribution":"1059"} ,"1489":{"x":116.2237,"y":40.3395,"region":"昌平区","Distribution":"58429"} ,"1490":{"x":116.2237,"y":40.3595,"region":"昌平区","Distribution":"10133"} ,"1491":{"x":116.2237,"y":40.3795,"region":"昌平区","Distribution":"65277"} ,"1539":{"x":116.2437,"y":40.1395,"region":"昌平区","Distribution":"24173"} ,"1540":{"x":116.2437,"y":40.1595,"region":"昌平区","Distribution":"24007"} ,"1541":{"x":116.2437,"y":40.1795,"region":"昌平区","Distribution":"4739"} ,"1542":{"x":116.2437,"y":40.1995,"region":"昌平区","Distribution":"26653"} ,"1543":{"x":116.2437,"y":40.2195,"region":"昌平区","Distribution":"7147"} ,"1544":{"x":116.2437,"y":40.2395,"region":"昌平区","Distribution":"38289"} ,"1545":{"x":116.2437,"y":40.2595,"region":"昌平区","Distribution":"6019"} ,"1546":{"x":116.2437,"y":40.2795,"region":"昌平区","Distribution":"7696"} ,"1547":{"x":116.2437,"y":40.2995,"region":"昌平区","Distribution":"39686"} ,"1548":{"x":116.2437,"y":40.3195,"region":"昌平区","Distribution":"6627"} ,"1549":{"x":116.2437,"y":40.3395,"region":"昌平区","Distribution":"75474"} ,"1550":{"x":116.2437,"y":40.3595,"region":"昌平区","Distribution":"33111"} ,"1601":{"x":116.2637,"y":40.0995,"region":"昌平区","Distribution":"23588"} ,"1602":{"x":116.2637,"y":40.1195,"region":"昌平区","Distribution":"12613"} ,"1603":{"x":116.2637,"y":40.1395,"region":"昌平区","Distribution":"47234"} ,"1604":{"x":116.2637,"y":40.1595,"region":"昌平区","Distribution":"12398"} ,"1605":{"x":116.2637,"y":40.1795,"region":"昌平区","Distribution":"19694"} ,"1606":{"x":116.2637,"y":40.1995,"region":"昌平区","Distribution":"7541"} ,"1607":{"x":116.2637,"y":40.2195,"region":"昌平区","Distribution":"15300"} ,"1608":{"x":116.2637,"y":40.2395,"region":"昌平区","Distribution":"33780"} ,"1609":{"x":116.2637,"y":40.2595,"region":"昌平区","Distribution":"9735"} ,"1610":{"x":116.2637,"y":40.2795,"region":"昌平区","Distribution":"28882"} ,"1611":{"x":116.2637,"y":40.2995,"region":"昌平区","Distribution":"2553"} ,"1612":{"x":116.2637,"y":40.3195,"region":"昌平区","Distribution":"70894"} ,"1613":{"x":116.2637,"y":40.3395,"region":"昌平区","Distribution":"15593"} ,"1614":{"x":116.2637,"y":40.3595,"region":"昌平区","Distribution":"65438"} ,"1615":{"x":116.2637,"y":40.3795,"region":"昌平区","Distribution":"15177"} ,"1666":{"x":116.2837,"y":40.0995,"region":"昌平区","Distribution":"2650"} ,"1667":{"x":116.2837,"y":40.1195,"region":"昌平区","Distribution":"42065"} ,"1668":{"x":116.2837,"y":40.1395,"region":"昌平区","Distribution":"43878"} ,"1669":{"x":116.2837,"y":40.1595,"region":"昌平区","Distribution":"19407"} ,"1670":{"x":116.2837,"y":40.1795,"region":"昌平区","Distribution":"4386"} ,"1671":{"x":116.2837,"y":40.1995,"region":"昌平区","Distribution":"21768"} ,"1672":{"x":116.2837,"y":40.2195,"region":"昌平区","Distribution":"24997"} ,"1673":{"x":116.2837,"y":40.2395,"region":"昌平区","Distribution":"13121"} ,"1674":{"x":116.2837,"y":40.2595,"region":"昌平区","Distribution":"14686"} ,"1675":{"x":116.2837,"y":40.2795,"region":"昌平区","Distribution":"1351"} ,"1676":{"x":116.2837,"y":40.2995,"region":"昌平区","Distribution":"28589"} ,"1677":{"x":116.2837,"y":40.3195,"region":"昌平区","Distribution":"79302"} ,"1678":{"x":116.2837,"y":40.3395,"region":"昌平区","Distribution":"16945"} ,"1679":{"x":116.2837,"y":40.3595,"region":"昌平区","Distribution":"2359"} ,"1729":{"x":116.3037,"y":40.0795,"region":"昌平区","Distribution":"3128"} ,"1730":{"x":116.3037,"y":40.0995,"region":"昌平区","Distribution":"1710"} ,"1731":{"x":116.3037,"y":40.1195,"region":"昌平区","Distribution":"45245"} ,"1732":{"x":116.3037,"y":40.1395,"region":"昌平区","Distribution":"42169"} ,"1733":{"x":116.3037,"y":40.1595,"region":"昌平区","Distribution":"59810"} ,"1734":{"x":116.3037,"y":40.1795,"region":"昌平区","Distribution":"1663"} ,"1735":{"x":116.3037,"y":40.1995,"region":"昌平区","Distribution":"72148"} ,"1736":{"x":116.3037,"y":40.2195,"region":"昌平区","Distribution":"10182"} ,"1737":{"x":116.3037,"y":40.2395,"region":"昌平区","Distribution":"17805"} ,"1738":{"x":116.3037,"y":40.2595,"region":"昌平区","Distribution":"43248"} ,"1739":{"x":116.3037,"y":40.2795,"region":"昌平区","Distribution":"57026"} ,"1740":{"x":116.3037,"y":40.2995,"region":"昌平区","Distribution":"3789"} ,"1741":{"x":116.3037,"y":40.3195,"region":"昌平区","Distribution":"21352"} ,"1742":{"x":116.3037,"y":40.3395,"region":"昌平区","Distribution":"58086"} ,"1743":{"x":116.3037,"y":40.3595,"region":"昌平区","Distribution":"19174"} ,"1744":{"x":116.3037,"y":40.3795,"region":"昌平区","Distribution":"15666"} ,"1792":{"x":116.3237,"y":40.0595,"region":"昌平区","Distribution":"20059"} ,"1793":{"x":116.3237,"y":40.0795,"region":"昌平区","Distribution":"43435"} ,"1794":{"x":116.3237,"y":40.0995,"region":"昌平区","Distribution":"14073"} ,"1795":{"x":116.3237,"y":40.1195,"region":"昌平区","Distribution":"59626"} ,"1796":{"x":116.3237,"y":40.1395,"region":"昌平区","Distribution":"23395"} ,"1797":{"x":116.3237,"y":40.1595,"region":"昌平区","Distribution":"18577"} ,"1798":{"x":116.3237,"y":40.1795,"region":"昌平区","Distribution":"543"} ,"1799":{"x":116.3237,"y":40.1995,"region":"昌平区","Distribution":"9736"} ,"1800":{"x":116.3237,"y":40.2195,"region":"昌平区","Distribution":"27851"} ,"1801":{"x":116.3237,"y":40.2395,"region":"昌平区","Distribution":"43491"} ,"1802":{"x":116.3237,"y":40.2595,"region":"昌平区","Distribution":"36871"} ,"1803":{"x":116.3237,"y":40.2795,"region":"昌平区","Distribution":"8343"} ,"1804":{"x":116.3237,"y":40.2995,"region":"昌平区","Distribution":"8005"} ,"1805":{"x":116.3237,"y":40.3195,"region":"昌平区","Distribution":"7734"} ,"1806":{"x":116.3237,"y":40.3395,"region":"昌平区","Distribution":"8066"} ,"1807":{"x":116.3237,"y":40.3595,"region":"昌平区","Distribution":"38990"} ,"1808":{"x":116.3237,"y":40.3795,"region":"昌平区","Distribution":"366"} ,"1859":{"x":116.3437,"y":40.0795,"region":"昌平区","Distribution":"47049"} ,"1860":{"x":116.3437,"y":40.0995,"region":"昌平区","Distribution":"26640"} ,"1861":{"x":116.3437,"y":40.1195,"region":"昌平区","Distribution":"91157"} ,"1862":{"x":116.3437,"y":40.1395,"region":"昌平区","Distribution":"601"} ,"1863":{"x":116.3437,"y":40.1595,"region":"昌平区","Distribution":"53898"} ,"1864":{"x":116.3437,"y":40.1795,"region":"昌平区","Distribution":"21452"} ,"1865":{"x":116.3437,"y":40.1995,"region":"昌平区","Distribution":"5445"} ,"1866":{"x":116.3437,"y":40.2195,"region":"昌平区","Distribution":"21070"} ,"1867":{"x":116.3437,"y":40.2395,"region":"昌平区","Distribution":"77971"} ,"1868":{"x":116.3437,"y":40.2595,"region":"昌平区","Distribution":"26363"} ,"1869":{"x":116.3437,"y":40.2795,"region":"昌平区","Distribution":"10097"} ,"1870":{"x":116.3437,"y":40.2995,"region":"昌平区","Distribution":"21817"} ,"1871":{"x":116.3437,"y":40.3195,"region":"昌平区","Distribution":"24682"} ,"1872":{"x":116.3437,"y":40.3395,"region":"昌平区","Distribution":"21054"} ,"1873":{"x":116.3437,"y":40.3595,"region":"昌平区","Distribution":"72514"} ,"1926":{"x":116.3637,"y":40.0795,"region":"昌平区","Distribution":"17493"} ,"1927":{"x":116.3637,"y":40.0995,"region":"昌平区","Distribution":"8727"} ,"1928":{"x":116.3637,"y":40.1195,"region":"昌平区","Distribution":"13722"} ,"1929":{"x":116.3637,"y":40.1395,"region":"昌平区","Distribution":"80531"} ,"1930":{"x":116.3637,"y":40.1595,"region":"昌平区","Distribution":"21406"} ,"1931":{"x":116.3637,"y":40.1795,"region":"昌平区","Distribution":"5836"} ,"1932":{"x":116.3637,"y":40.1995,"region":"昌平区","Distribution":"26668"} ,"1933":{"x":116.3637,"y":40.2195,"region":"昌平区","Distribution":"35779"} ,"1934":{"x":116.3637,"y":40.2395,"region":"昌平区","Distribution":"13317"} ,"1935":{"x":116.3637,"y":40.2595,"region":"昌平区","Distribution":"224"} ,"1936":{"x":116.3637,"y":40.2795,"region":"昌平区","Distribution":"39996"} ,"1937":{"x":116.3637,"y":40.2995,"region":"昌平区","Distribution":"32494"} ,"1938":{"x":116.3637,"y":40.3195,"region":"昌平区","Distribution":"57783"} ,"1939":{"x":116.3637,"y":40.3395,"region":"昌平区","Distribution":"51382"} ,"1940":{"x":116.3637,"y":40.3595,"region":"昌平区","Distribution":"9431"} ,"1991":{"x":116.3837,"y":40.0595,"region":"昌平区","Distribution":"28833"} ,"1992":{"x":116.3837,"y":40.0795,"region":"昌平区","Distribution":"93129"} ,"1993":{"x":116.3837,"y":40.0995,"region":"昌平区","Distribution":"33939"} ,"1994":{"x":116.3837,"y":40.1195,"region":"昌平区","Distribution":"41502"} ,"1995":{"x":116.3837,"y":40.1395,"region":"昌平区","Distribution":"36464"} ,"1996":{"x":116.3837,"y":40.1595,"region":"昌平区","Distribution":"68377"} ,"1997":{"x":116.3837,"y":40.1795,"region":"昌平区","Distribution":"9322"} ,"1998":{"x":116.3837,"y":40.1995,"region":"昌平区","Distribution":"24382"} ,"1999":{"x":116.3837,"y":40.2195,"region":"昌平区","Distribution":"33191"} ,"2000":{"x":116.3837,"y":40.2395,"region":"昌平区","Distribution":"32676"} ,"2001":{"x":116.3837,"y":40.2595,"region":"昌平区","Distribution":"68541"} ,"2002":{"x":116.3837,"y":40.2795,"region":"昌平区","Distribution":"594"} ,"2003":{"x":116.3837,"y":40.2995,"region":"昌平区","Distribution":"28770"} ,"2004":{"x":116.3837,"y":40.3195,"region":"昌平区","Distribution":"12898"} ,"2005":{"x":116.3837,"y":40.3395,"region":"昌平区","Distribution":"12113"} ,"2056":{"x":116.4037,"y":40.0595,"region":"昌平区","Distribution":"8892"} ,"2057":{"x":116.4037,"y":40.0795,"region":"昌平区","Distribution":"12246"} ,"2058":{"x":116.4037,"y":40.0995,"region":"昌平区","Distribution":"26026"} ,"2059":{"x":116.4037,"y":40.1195,"region":"昌平区","Distribution":"36475"} ,"2060":{"x":116.4037,"y":40.1395,"region":"昌平区","Distribution":"35620"} ,"2061":{"x":116.4037,"y":40.1595,"region":"昌平区","Distribution":"200"} ,"2062":{"x":116.4037,"y":40.1795,"region":"昌平区","Distribution":"11159"} ,"2063":{"x":116.4037,"y":40.1995,"region":"昌平区","Distribution":"17785"} ,"2064":{"x":116.4037,"y":40.2195,"region":"昌平区","Distribution":"51736"} ,"2065":{"x":116.4037,"y":40.2395,"region":"昌平区","Distribution":"31453"} ,"2066":{"x":116.4037,"y":40.2595,"region":"昌平区","Distribution":"10672"} ,"2067":{"x":116.4037,"y":40.2795,"region":"昌平区","Distribution":"51469"} ,"2068":{"x":116.4037,"y":40.2995,"region":"昌平区","Distribution":"30425"} ,"2069":{"x":116.4037,"y":40.3195,"region":"昌平区","Distribution":"793"} ,"2120":{"x":116.4237,"y":40.0795,"region":"昌平区","Distribution":"186"} ,"2121":{"x":116.4237,"y":40.0995,"region":"昌平区","Distribution":"7812"} ,"2122":{"x":116.4237,"y":40.1195,"region":"昌平区","Distribution":"13653"} ,"2123":{"x":116.4237,"y":40.1395,"region":"昌平区","Distribution":"27149"} ,"2124":{"x":116.4237,"y":40.1595,"region":"昌平区","Distribution":"71557"} ,"2125":{"x":116.4237,"y":40.1795,"region":"昌平区","Distribution":"18784"} ,"2126":{"x":116.4237,"y":40.1995,"region":"昌平区","Distribution":"93695"} ,"2127":{"x":116.4237,"y":40.2195,"region":"昌平区","Distribution":"6872"} ,"2128":{"x":116.4237,"y":40.2395,"region":"昌平区","Distribution":"32885"} ,"2129":{"x":116.4237,"y":40.2595,"region":"昌平区","Distribution":"3101"} ,"2130":{"x":116.4237,"y":40.2795,"region":"昌平区","Distribution":"51532"} ,"2131":{"x":116.4237,"y":40.2995,"region":"昌平区","Distribution":"574"} ,"2132":{"x":116.4237,"y":40.3195,"region":"昌平区","Distribution":"9463"} ,"2180":{"x":116.4437,"y":40.0795,"region":"昌平区","Distribution":"83365"} ,"2181":{"x":116.4437,"y":40.0995,"region":"昌平区","Distribution":"35777"} ,"2182":{"x":116.4437,"y":40.1195,"region":"昌平区","Distribution":"19586"} ,"2183":{"x":116.4437,"y":40.1395,"region":"昌平区","Distribution":"29430"} ,"2184":{"x":116.4437,"y":40.1595,"region":"昌平区","Distribution":"7949"} ,"2185":{"x":116.4437,"y":40.1795,"region":"昌平区","Distribution":"14595"} ,"2186":{"x":116.4437,"y":40.1995,"region":"昌平区","Distribution":"2126"} ,"2187":{"x":116.4437,"y":40.2195,"region":"昌平区","Distribution":"29940"} ,"2188":{"x":116.4437,"y":40.2395,"region":"昌平区","Distribution":"55327"} ,"2189":{"x":116.4437,"y":40.2595,"region":"昌平区","Distribution":"85241"} ,"2190":{"x":116.4437,"y":40.2795,"region":"昌平区","Distribution":"12712"} ,"2191":{"x":116.4437,"y":40.2995,"region":"昌平区","Distribution":"22079"} ,"2192":{"x":116.4437,"y":40.3195,"region":"昌平区","Distribution":"50473"} ,"2234":{"x":116.4637,"y":40.0995,"region":"昌平区","Distribution":"17662"} ,"2235":{"x":116.4637,"y":40.1195,"region":"昌平区","Distribution":"18485"} ,"2236":{"x":116.4637,"y":40.1395,"region":"昌平区","Distribution":"33978"} ,"2237":{"x":116.4637,"y":40.1595,"region":"昌平区","Distribution":"69683"} ,"2238":{"x":116.4637,"y":40.1795,"region":"昌平区","Distribution":"6137"} ,"2239":{"x":116.4637,"y":40.1995,"region":"昌平区","Distribution":"10903"} ,"2240":{"x":116.4637,"y":40.2195,"region":"昌平区","Distribution":"29627"} ,"2241":{"x":116.4637,"y":40.2395,"region":"昌平区","Distribution":"47298"} ,"2242":{"x":116.4637,"y":40.2595,"region":"昌平区","Distribution":"22017"} ,"2243":{"x":116.4637,"y":40.2795,"region":"昌平区","Distribution":"68255"} ,"2289":{"x":116.4837,"y":40.0995,"region":"昌平区","Distribution":"8251"} ,"2290":{"x":116.4837,"y":40.1195,"region":"昌平区","Distribution":"17452"} ,"2291":{"x":116.4837,"y":40.1395,"region":"昌平区","Distribution":"31710"} ,"2292":{"x":116.4837,"y":40.1595,"region":"昌平区","Distribution":"448"} ,"2293":{"x":116.4837,"y":40.1795,"region":"昌平区","Distribution":"13247"} ,"2294":{"x":116.4837,"y":40.2395,"region":"昌平区","Distribution":"43771"} ,"2295":{"x":116.4837,"y":40.2595,"region":"昌平区","Distribution":"17434"} ,"2345":{"x":116.5037,"y":40.2595,"region":"昌平区","Distribution":"41447"} }}]